{
  "introduction_available": "Available time",
  "introduction_unavailable": "Unavailable time",
  "select_teacher_hint": "Select the teacher",
  "select_teacher_DNE_hint": "Please select the teacher to view the schedule",
  "select_teacher_no_officehour": "Have no OfficeHour activity for the time being",
  "go_appointment": "Make an appointment",
  "ban_time_button": "Disable a time period",
  "ban_date": "Date",
  "ban_time": "Time Period",
  "ban_time_upload": "Upload",
  "ban_time_cancel": "Cancel",
  "tag1": "men's wear",
  "tag2": "women's wear",
  "tag3": "electronics",
  "tag4": "mobile phones",
  "tag5": "Ipad",
  "tag6": "laptops",
  "tag7": "home appliances",
  "tag8": "furniture",
  "tag9": "clothing",
  "tag10": "shoes",
  "tag11": "bags",
  "tag12": "make-up items",
  "tag13": "books",
  "tag14": "sports equipment",
  "tag15": "gaming devices",
  "tag16": "musical instruments",
  "tag17": "car accessories",
  "tag18": "kids' items",
  "tag19": "collection",
  "tag20": "pet supplies",
  "recommend_api_failure": "Failed to get items",
  "search_api_failure": "Failed to get items",
  "search_get_none": "No Goods found",
  "search_empty": "Please enter the search content",
  "empty_hint": "No product appears to have been searched",
  "refresh": "Refresh",
  "item_list_title": "Item List (Guess what you like)",
  "bad_request_refresh": "Refresh the page"
}

